fateh/__init__.py
fateh/fateh.py
fateh-0.1.0.dist-info/LICENSE
fateh-0.1.0.dist-info/METADATA
fateh-0.1.0.dist-info/WHEEL
fateh-0.1.0.dist-info/entry_points.txt
fateh-0.1.0.dist-info/top_level.txt
fateh-0.1.0.dist-info/RECORD
