Metadata-Version: 2.1
Name: fateh
Version: 0.1.0
Summary: A Python package for TOPSIS score calculation
Home-page: https://github.com/yourusername/fateh
Author: abhaijeet
Author-email: your_email@example.com
Classifier: Programming Language :: Python :: 3
Classifier: License :: OSI Approved :: MIT License
Classifier: Operating System :: OS Independent
Requires-Python: >=3.6
License-File: LICENSE
Requires-Dist: pandas
Requires-Dist: numpy
